compilecls/__init__.py
compilecls-1.0.0.dist-info/METADATA
compilecls-1.0.0.dist-info/WHEEL
compilecls-1.0.0.dist-info/top_level.txt
compilecls-1.0.0.dist-info/RECORD
