Metadata-Version: 2.1
Name: compilecls
Version: 1.0.0
Summary: Compiles cls
Home-page: UNKNOWN
Author: TOS follower
Author-email: nick.faltermeier@gmx.de
License: UNKNOWN
Keywords: python
Platform: UNKNOWN
Classifier: Operating System :: Microsoft :: Windows
